_jsonnet.cpython-39-darwin.so
jsonnet-0.21.0.dist-info/RECORD
jsonnet-0.21.0.dist-info/WHEEL
jsonnet-0.21.0.dist-info/top_level.txt
jsonnet-0.21.0.dist-info/METADATA
jsonnet-0.21.0.dist-info/licenses/LICENSE
