Metadata-Version: 2.4
Name: jsonnet
Version: 0.21.0
Summary: Python bindings for Jsonnet - The data templating language 
Home-page: https://jsonnet.org
Author: David Cunningham
Author-email: dcunnin@google.com
License: Apache License 2.0
Project-URL: Source, https://github.com/google/jsonnet
License-File: LICENSE
Dynamic: author
Dynamic: author-email
Dynamic: home-page
Dynamic: license
Dynamic: license-file
Dynamic: project-url
Dynamic: summary
